README.rst
pyproject.toml
setup.cfg
doc/source/conf.py
mccli/VERSION
mccli/__init__.py
mccli/_version.py
mccli/click_utils.py
mccli/exceptions.py
mccli/info_utils.py
mccli/init_utils.py
mccli/logging.py
mccli/mccli.py
mccli/motley_cue_client.py
mccli/scp_utils.py
mccli/ssh_wrapper.py
mccli.egg-info/PKG-INFO
mccli.egg-info/SOURCES.txt
mccli.egg-info/dependency_links.txt
mccli.egg-info/entry_points.txt
mccli.egg-info/requires.txt
mccli.egg-info/top_level.txt