Metadata-Version: 2.4
Name: mccli
Version: 0.7.5
Summary: SSH client wrapper for SSH with access token
Home-page: https://github.com/dianagudu/mccli
Author: Diana Gudu
Author-email: gudu@kit.edu
License: MIT
Project-URL: Bug Tracker, https://github.com/dianagudu/mccli/issues
Project-URL: Documentation, https://mccli.readthedocs.io
Classifier: Development Status :: 3 - Alpha
Classifier: Environment :: Console
Classifier: Environment :: Web Environment
Classifier: Intended Audience :: Developers
Classifier: Intended Audience :: Information Technology
Classifier: Intended Audience :: Science/Research
Classifier: Intended Audience :: System Administrators
Classifier: License :: OSI Approved :: MIT License
Classifier: Operating System :: OS Independent
Classifier: Natural Language :: English
Classifier: Programming Language :: Python :: 3
Classifier: Programming Language :: Python :: 3.7
Classifier: Programming Language :: Python :: 3.8
Classifier: Programming Language :: Python :: 3.9
Classifier: Programming Language :: Python :: 3.10
Classifier: Topic :: System :: Systems Administration
Classifier: Topic :: System :: Systems Administration :: Authentication/Directory
Classifier: Topic :: Utilities
Requires-Dist: pexpect
Requires-Dist: liboidcagent
Requires-Dist: requests
Requires-Dist: requests-cache
Requires-Dist: click>=8.0.0
Requires-Dist: click-option-group
Requires-Dist: click-logging
Requires-Dist: rfc3986
Requires-Dist: flaat>=1.0.0
